Converse/__init__.py
Converse/config/__init__.py
Converse/config/config.py
Converse/config/task_config.py
Converse/demo/__init__.py
Converse/demo/chat_window_app.py
Converse/demo/client.py
Converse/demo/config_ui_backend.py
Converse/demo/dial_backend.py
Converse/demo/setup_config_ui.py
Converse/demo/shell.py
Converse/dialog_context/__init__.py
Converse/dialog_context/dialog_context.py
Converse/dialog_context/dialog_context_manager.py
Converse/dialog_info_layer/__init__.py
Converse/dialog_info_layer/dial_info.py
Converse/dialog_orchestrator/__init__.py
Converse/dialog_orchestrator/orchestrator.py
Converse/dialog_policy/__init__.py
Converse/dialog_policy/dial_policy.py
Converse/dialog_state_manager/__init__.py
Converse/dialog_state_manager/dial_state_manager.py
Converse/dialog_tree/__init__.py
Converse/dialog_tree/dial_tree.py
Converse/dialog_tree/tree_manager.py
Converse/entity/__init__.py
Converse/entity/entity.py
Converse/entity/entity_history.py
Converse/entity/entity_manager.py
Converse/entity_backend/__init__.py
Converse/entity_backend/entity_functions.py
Converse/entity_backend/entity_service_backend.py
Converse/nlu/__init__.py
Converse/nlu/protoc.py
Converse/nlu/intent_converse/__init__.py
Converse/nlu/intent_converse/bert_intent.py
Converse/nlu/intent_converse/client.py
Converse/nlu/intent_converse/dnnc_tinybert_inference_only.py
Converse/nlu/intent_converse/server.py
Converse/nlu/intent_converse/servicer.py
Converse/nlu/intent_converse/utils.py
Converse/nlu/intent_converse/TinyBERT/__init__.py
Converse/nlu/intent_converse/TinyBERT/data_augmentation.py
Converse/nlu/intent_converse/TinyBERT/general_distill.py
Converse/nlu/intent_converse/TinyBERT/pregenerate_training_data.py
Converse/nlu/intent_converse/TinyBERT/task_distill.py
Converse/nlu/intent_converse/TinyBERT/transformer/__init__.py
Converse/nlu/intent_converse/TinyBERT/transformer/file_utils.py
Converse/nlu/intent_converse/TinyBERT/transformer/modeling.py
converse_sfr-0.0.2.dist-info/LICENSE.txt
converse_sfr-0.0.2.dist-info/METADATA
converse_sfr-0.0.2.dist-info/WHEEL
converse_sfr-0.0.2.dist-info/entry_points.txt
converse_sfr-0.0.2.dist-info/top_level.txt
converse_sfr-0.0.2.dist-info/RECORD
