Metadata-Version: 2.1
Name: converse-sfr
Version: 0.0.2
Summary: A framework that facilitates creating task-oriented chatbot
Home-page: https://github.com/MetaMind/eloq_dial
Author: Salesforce Research
Author-email: converse.ai@salesforce.com
License: UNKNOWN
Project-URL: Bug Tracker, https://github.com/MetaMind/eloq_dial/issues
Platform: UNKNOWN
Classifier: Programming Language :: Python :: 3
Classifier: License :: OSI Approved :: BSD License
Classifier: Operating System :: OS Independent
Requires-Python: >=3.7
License-File: LICENSE.txt
Requires-Dist: black (==20.8b1)
Requires-Dist: grpcio (==1.27.2)
Requires-Dist: flake8 (==3.8.4)
Requires-Dist: flask (==1.1.1)
Requires-Dist: Flask-Cors (==3.0.9)
Requires-Dist: fuzzysearch (==0.7.0)
Requires-Dist: itsdangerous (==2.0.1)
Requires-Dist: jsonpickle (==1.4.2)
Requires-Dist: nltk (==3.6.6)
Requires-Dist: num2words (==0.5.10)
Requires-Dist: pony (==0.7.14)
Requires-Dist: protobuf (==3.15.0)
Requires-Dist: python-Levenshtein (==0.12.2)
Requires-Dist: thefuzz (==0.19.0)
Requires-Dist: pyyaml (==5.4)
Requires-Dist: redis (==3.5.3)
Requires-Dist: requests (==2.23.0)
Requires-Dist: scikit-learn (==0.22.2.post1)
Requires-Dist: wrapt-timeout-decorator (==1.3.1)
Requires-Dist: Jinja2 (<3.1.0)
